chio/__init__.py
chio/chio.py
chio/constants.py
chio/io.py
chio/patching.py
chio/types.py
chio/utils.py
chio/clients/__init__.py
chio/clients/b1183.py
chio/clients/b1365.py
chio/clients/b1600.py
chio/clients/b1788.py
chio/clients/b1796.py
chio/clients/b1797.py
chio/clients/b1800.py
chio/clients/b1817.py
chio/clients/b1820.py
chio/clients/b20120518.py
chio/clients/b20120703.py
chio/clients/b20120723.py
chio/clients/b20120725.py
chio/clients/b20120806.py
chio/clients/b20120818.py
chio/clients/b20121023.py
chio/clients/b20121028.py
chio/clients/b20121203.py
chio/clients/b20121207.py
chio/clients/b20121211.py
chio/clients/b20121212.py
chio/clients/b20121221.py
chio/clients/b20121224.py
chio/clients/b20121225.py
chio/clients/b20130118.py
chio/clients/b20130131.py
chio/clients/b20130209.py
chio/clients/b20130303.py
chio/clients/b20130418.py
chio/clients/b20130509.py
chio/clients/b20130604.py
chio/clients/b20130801.py
chio/clients/b20140528.py
chio/clients/b20140716.py
chio/clients/b20140731.py
chio/clients/b20141104.py
chio/clients/b20150826.py
chio/clients/b20150915.py
chio/clients/b20151106.py
chio/clients/b20151107.py
chio/clients/b20160404.py
chio/clients/b20161101.py
chio/clients/b20250306.py
chio/clients/b282.py
chio/clients/b291.py
chio/clients/b294.py
chio/clients/b296.py
chio/clients/b298.py
chio/clients/b312.py
chio/clients/b320.py
chio/clients/b323.py
chio/clients/b334.py
chio/clients/b338.py
chio/clients/b340.py
chio/clients/b342.py
chio/clients/b349.py
chio/clients/b354.py
chio/clients/b365.py
chio/clients/b374.py
chio/clients/b388.py
chio/clients/b402.py
chio/clients/b425.py
chio/clients/b452.py
chio/clients/b470.py
chio/clients/b487.py
chio/clients/b489.py
chio/clients/b490.py
chio/clients/b504.py
chio/clients/b535.py
chio/clients/b558.py
chio/clients/b591.py
chio/clients/b613.py
chio/clients/b634.py
chio/clients/b659.py
chio/clients/b695.py
chio-1.1.20.dist-info/licenses/LICENSE
chio-1.1.20.dist-info/METADATA
chio-1.1.20.dist-info/WHEEL
chio-1.1.20.dist-info/top_level.txt
chio-1.1.20.dist-info/RECORD
