Metadata-Version: 2.4
Name: chio
Version: 1.1.20
Summary: A python library for serializing and deserializing bancho packets.
Author: Lekuru
Author-email: contact@lekuru.xyz
Keywords: osu,osugame,python,bancho
License-File: LICENSE
Dynamic: author
Dynamic: author-email
Dynamic: description
Dynamic: description-content-type
Dynamic: keywords
Dynamic: license-file
Dynamic: summary
